pyTinySoundFont/SF2.py
pyTinySoundFont/SF2Presets.py
pyTinySoundFont/SF2Synth.py
pyTinySoundFont/SF2Synth.wasm
pyTinySoundFont/SF2SynthRT.py
pyTinySoundFont/__init__.py
pyTinySoundFont/wasm_binding.py
pyTinySoundFontWASM-0.1.0.dist-info/METADATA
pyTinySoundFontWASM-0.1.0.dist-info/WHEEL
pyTinySoundFontWASM-0.1.0.dist-info/top_level.txt
pyTinySoundFontWASM-0.1.0.dist-info/RECORD
