Metadata-Version: 2.1
Name: pyTinySoundFontWASM
Version: 0.1.0
Summary: Python port of TinySoundFont (using WASM)
Home-page: https://github.com/fynv/pyTinySoundFont/wasm
Author: Fei Yang
Author-email: hyangfeih@gmail.com
License: MIT
Keywords: synthesizer soundfont sf2
Platform: UNKNOWN
Requires-Dist: wasmtime
